{
    "updater": {
        "versions": {
            "app": {
                "ver": "5.0.0"
            },
            "profile": {
                "ver": "5.0.0"
            },
            "storage": {
                "ver": "5.0.0"
            },
            "shortcuts": {
                "ver": "5.0.0"
            },
            "lambda": {
                "ver": "5.0.0",
                "date": "2017-09-14T19:00:00+04:00"
            },
            "skills": {
                "ver": "5.0.0"
            }
        }
    },
    "analytics": {
        "allowCmdCollect": true
    }
}
